ezlock/__init__.py
ezlock/lock.py
ezlock-0.1.3.dist-info/LICENSE.txt
ezlock-0.1.3.dist-info/WHEEL
ezlock-0.1.3.dist-info/METADATA
ezlock-0.1.3.dist-info/RECORD
